amazon_q_rule_manager/__init__.py
amazon_q_rule_manager/cli.py
amazon_q_rule_manager/core.py
amazon_q_rule_manager/models.py
amazon_q_rule_manager/data/rules_catalog.json
amazon_q_rule_manager/tests/__init__.py
amazon_q_rule_manager/tests/test_models.py
amazon_q_rule_manager-1.0.2.dist-info/licenses/LICENSE
amazon_q_rule_manager-1.0.2.dist-info/METADATA
amazon_q_rule_manager-1.0.2.dist-info/WHEEL
amazon_q_rule_manager-1.0.2.dist-info/entry_points.txt
amazon_q_rule_manager-1.0.2.dist-info/top_level.txt
amazon_q_rule_manager-1.0.2.dist-info/RECORD
