Metadata-Version: 2.4
Name: amazon-q-rule-manager
Version: 1.0.2
Summary: A robust manager for Amazon Q Developer rules with global and workspace support
Home-page: https://github.com/zerodaysec/amazonq-rules
Author: Amazon Q Rules Team
Author-email: Amazon Q Rules Team <support@example.com>
License: MIT
Project-URL: Homepage, https://github.com/jon-the-dev/amazon-q-rule-manager
Project-URL: Documentation, https://github.com/jon-the-dev/amazon-q-rule-manager/blob/main/README.md
Project-URL: Repository, https://github.com/jon-the-dev/amazon-q-rule-manager
Project-URL: Bug Reports, https://github.com/jon-the-dev/amazon-q-rule-manager/issues
Keywords: amazon-q,developer,rules,code-quality,aws,terraform,python
Classifier: Development Status :: 4 - Beta
Classifier: Intended Audience :: Developers
Classifier: Topic :: Software Development :: Code Generators
Classifier: Topic :: Software Development :: Quality Assurance
Classifier: License :: OSI Approved :: MIT License
Classifier: Programming Language :: Python :: 3
Classifier: Programming Language :: Python :: 3.12
Classifier: Programming Language :: Python :: 3.13
Classifier: Operating System :: OS Independent
Requires-Python: >=3.12
License-File: LICENSE
Requires-Dist: python-dotenv>=1.0.0
Requires-Dist: requests>=2.31.0
Requires-Dist: click>=8.1.0
Requires-Dist: rich>=13.0.0
Requires-Dist: pydantic>=2.0.0
Requires-Dist: appdirs>=1.4.4
Provides-Extra: dev
Requires-Dist: pytest>=7.0.0; extra == "dev"
Requires-Dist: pytest-cov>=4.0.0; extra == "dev"
Requires-Dist: black>=23.0.0; extra == "dev"
Requires-Dist: flake8>=6.0.0; extra == "dev"
Requires-Dist: mypy>=1.0.0; extra == "dev"
Requires-Dist: pre-commit>=3.0.0; extra == "dev"
Requires-Dist: twine>=4.0.0; extra == "dev"
Requires-Dist: build>=0.10.0; extra == "dev"
Dynamic: author
Dynamic: home-page
Dynamic: license-file
Dynamic: requires-python
